Metadata-Version: 2.1
Name: example-package-hello-world
Version: 0.0.1
Summary: Hello World Demo Description
Home-page: https://github.com/pypa/sampleproject
Author: KooBro
Author-email: koobro@qq.com
Project-URL: Bug Tracker, https://github.com/pypa/sampleproject/issues
Classifier: Programming Language :: Python :: 3
Classifier: License :: OSI Approved :: MIT License
Classifier: Operating System :: OS Independent
Requires-Python: >=3.6
License-File: LICENSE
